vecutils/__init__.py
vecutils/qdrant.py
vecutils/utils.py
vecutils/scripts/qdrant.py
vecutils-0.0.11.dist-info/METADATA
vecutils-0.0.11.dist-info/WHEEL
vecutils-0.0.11.dist-info/RECORD
