Metadata-Version: 2.1
Name: vecutils
Version: 0.0.11
Summary: Add your description here
Author-email: Yevgnen Koh <wherejoystarts@gmail.com>
Requires-Python: >=3.10
Requires-Dist: qdrant-client>=1.7.1
Requires-Dist: tqdm>=4.66.1
